[
  {"id":0,  "name":"BROKEN ITEM",      "kind":"misc",   "price":1,     "name_zh":"破損物品"},
  {"id":1,  "name":"LONG SWORD",       "kind":"weapon", "price":25,    "dmg":"1d8",  "swings":1, "use":["F","S","L","B"], "name_zh":"長劍"},
  {"id":2,  "name":"SHORT SWORD",      "kind":"weapon", "price":15,    "dmg":"1d6",  "swings":1, "use":["F","S","L","T","N","B"], "name_zh":"短劍"},
  {"id":3,  "name":"MACE",             "kind":"weapon", "price":30,    "dmg":"1d6",  "swings":1, "use":["F","P","B"], "name_zh":"釘頭錘"},
  {"id":4,  "name":"STAFF",            "kind":"weapon", "price":5,     "dmg":"1d4",  "swings":1, "use":["F","M","P","B"], "name_zh":"法杖"},
  {"id":5,  "name":"DAGGER",           "kind":"weapon", "price":5,     "dmg":"1d4",  "swings":1, "use":["F","M","P","T","B","N","S","L"], "name_zh":"匕首"},
  {"id":6,  "name":"LEATHER ARMOR",    "kind":"armor",  "price":50,    "ac_mod":-1,  "use":["F","P","T","B","S","L","N"], "name_zh":"皮甲"},
  {"id":7,  "name":"CHAIN MAIL",       "kind":"armor",  "price":90,    "ac_mod":-2,  "use":["F","P","S","L","N"], "name_zh":"鎖子甲"},
  {"id":8,  "name":"PLATE MAIL",       "kind":"armor",  "price":750,   "ac_mod":-3,  "use":["F","S","L"], "name_zh":"板甲"},
  {"id":9,  "name":"BREAST PLATE",     "kind":"armor",  "price":200,   "ac_mod":-2,  "use":["F","P","S","L","N"], "name_zh":"胸甲"},
  {"id":10, "name":"SMALL SHIELD",     "kind":"shield", "price":20,    "ac_mod":-1,  "use":["F","P","T","B","S","L","N"], "name_zh":"小盾"},
  {"id":11, "name":"LARGE SHIELD",     "kind":"shield", "price":40,    "ac_mod":-2,  "use":["F","P","S","L"], "name_zh":"大盾"},
  {"id":12, "name":"HELM",             "kind":"helmet", "price":100,   "ac_mod":-1,  "use":["F","P","S","L","N"], "name_zh":"頭盔"},
  {"id":13, "name":"GAUNTLETS",        "kind":"gloves", "price":6000,  "ac_mod":-2,  "use":["F","S","L","N"], "name_zh":"鎧甲護手"},
  {"id":14, "name":"LONG SWORD +1",    "kind":"weapon", "price":1500,  "dmg":"1d8+1","swings":1, "use":["F","S","L","B"], "name_zh":"長劍+1"},
  {"id":15, "name":"MACE +1",          "kind":"weapon", "price":1500,  "dmg":"1d6+1","swings":1, "use":["F","P","B"], "name_zh":"釘頭錘+1"},
  {"id":16, "name":"STAFF OF MOGREF",  "kind":"weapon", "price":3500,  "dmg":"1d4",  "swings":1, "spell":"MOGREF", "use":["M","B"], "name_zh":"莫格雷夫法杖"},
  {"id":17, "name":"WERDNA'S AMULET",  "kind":"misc",   "price":999999,"special":1, "name_zh":"沃登納護身符"},
  {"id":18, "name":"POTION OF DIOS",   "kind":"potion", "price":500,   "spell":"DIOS", "name_zh":"治療藥水"},
  {"id":19, "name":"POTION OF LATUMOFIS","kind":"potion","price":250,  "spell":"LATUMOFIS","name_zh":"解毒藥水"},
  {"id":20, "name":"SCROLL OF KATINO", "kind":"scroll", "price":500,   "spell":"KATINO", "name_zh":"卡提諾卷軸"},
  {"id":21, "name":"SCROLL OF BADIOS", "kind":"scroll", "price":500,   "spell":"BADIOS", "name_zh":"巴迪奧斯卷軸"},
  {"id":22, "name":"BLADE CUSINART",   "kind":"weapon", "price":15000, "dmg":"10d10","swings":1, "use":["F","S","L"], "name_zh":"庫西納特之刃"},
  {"id":23, "name":"MURAMASA BLADE",   "kind":"weapon", "price":1000000,"dmg":"10d10","swings":2, "use":["S"], "name_zh":"村正之刃"},
  {"id":24, "name":"SHURIKEN",         "kind":"weapon", "price":1000000,"dmg":"8d8","swings":3,"use":["N"], "name_zh":"手裏劍"},
  {"id":25, "name":"RING OF MOVEMENT", "kind":"misc",   "price":5000,  "spell":"DIALKO","name_zh":"行動戒指"},
  {"id":26, "name":"RING OF HEALING",  "kind":"misc",   "price":300000,"name_zh":"治癒戒指"},
  {"id":27, "name":"AMULET OF MAKANITO","kind":"misc",  "price":4000,  "spell":"MAKANITO","name_zh":"馬卡尼托護符"},
  {"id":28, "name":"COINS",            "kind":"misc",   "price":100,   "name_zh":"錢幣"},
  {"id":29, "name":"BOLTAC'S NOTE",    "kind":"misc",   "price":1,     "name_zh":"波塔克的字條"}
]
